odoo/addons/sql_export_delta/README.rst
odoo/addons/sql_export_delta/__init__.py
odoo/addons/sql_export_delta/__manifest__.py
odoo/addons/sql_export_delta/hooks.py
odoo/addons/sql_export_delta/i18n/it.po
odoo/addons/sql_export_delta/i18n/sql_export_delta.pot
odoo/addons/sql_export_delta/models/__init__.py
odoo/addons/sql_export_delta/models/sql_export.py
odoo/addons/sql_export_delta/readme/CONFIGURE.md
odoo/addons/sql_export_delta/readme/CONTRIBUTORS.md
odoo/addons/sql_export_delta/readme/DESCRIPTION.md
odoo/addons/sql_export_delta/static/description/icon.png
odoo/addons/sql_export_delta/static/description/index.html
odoo/addons/sql_export_delta/tests/__init__.py
odoo/addons/sql_export_delta/tests/test_sql_export_delta.py
odoo/addons/sql_export_delta/views/sql_export.xml
odoo/addons/sql_export_delta/wizards/__init__.py
odoo/addons/sql_export_delta/wizards/sql_file_wizard.py
odoo_addon_sql_export_delta-16.0.1.0.0.3.dist-info/METADATA
odoo_addon_sql_export_delta-16.0.1.0.0.3.dist-info/WHEEL
odoo_addon_sql_export_delta-16.0.1.0.0.3.dist-info/top_level.txt
odoo_addon_sql_export_delta-16.0.1.0.0.3.dist-info/RECORD
